[  
      {
        "id": 1,
        "nomeCandidato": "João da Silva",
        "vaga": "Desenvolvedor Full Stack",
        "redesSociais": {
          "linkedin": "https://www.linkedin.com/in/joaosilva/",
          "github": "https://github.com/joaosilva"
        },
        "descricao": "João tem experiência em desenvolvimento web e mobile, domina React e Node.js, além de ter conhecimento em bancos de dados SQL e NoSQL.",
        "consideracoes": "João já realizou o teste técnico e obteve um bom resultado.",
        "dataHora": "2023-04-15T14:00:00-03:00",
        "responsaveis": [
          {
            "id": 1,
            "nome": "Luciana Souza",
            "perfil": "RH"
          },
          {
            "id": 2,
            "nome": "Pedro Oliveira",
            "perfil": "Tecnologia"
          },
          {
            "id": 3,
            "nome": "Maria Silva",
            "perfil": "Tecnologia"
          }
        ],
        "anexo": "https://drive.google.com/file/d/1XdPAkURBm_lAhXAmhHqbEsgZJxKcG_GI/view?usp=sharing"
      }, 
      {
        "id": 2,
        "nomeCandidato": "Ana Paula Pereira",
        "vaga": "Analista de Sistemas",
        "redesSociais": {
          "linkedin": "https://www.linkedin.com/in/anapaulapereira/",
          "github": "https://github.com/anapereira"
        },
        "descricao": "Ana Paula é formada em Sistemas de Informação e tem experiência em desenvolvimento de software.",
        "consideracoes": "",
        "dataHora": "2023-04-16T10:00:00-03:00",
        "responsaveis": [
          {
            "id": 1,
            "nome": "Luciana Souza",
            "perfil": "RH"
          },
          {
            "id": 4,
            "nome": "Thiago Santos",
            "perfil": "Tecnologia"
          }
        ],
        "anexo": "https://drive.google.com/file/d/1d-05pgyNxxL_4lNwoSWFbm9RLTtfO84b/view?usp=sharing"
      },
      {
        "id": 3,
        "nomeCandidato": "Pedro Henrique Oliveira",
        "vaga": "Desenvolvedor Frontend",
        "redesSociais": {
          "linkedin": "https://www.linkedin.com/in/pedroholiveira/",
          "github": "https://github.com/pedroholiveira"
        },
        "descricao": "Pedro é especialista em desenvolvimento Frontend e possui habilidades em React, Vue.js e Angular.",
        "consideracoes": "",
        "dataHora": "2023-04-20T16:00:00-03:00",
        "responsaveis": [
          {
            "id": 1,
            "nome": "Luciana Souza",
            "perfil": "RH"
          }
        ],
        "anexo": ""
      }
    ]
  
  
